kws/__init__.py
kws/features.py
kws-0.1.0.dist-info/METADATA
kws-0.1.0.dist-info/WHEEL
kws-0.1.0.dist-info/RECORD
