Metadata-Version: 2.4
Name: kws
Version: 0.1.0
Summary: Extract features from audio files
Author-email: Ngoc An Lam <anlam9614@gmail.com>
License-Expression: MIT
Requires-Python: >=3.8
Requires-Dist: librosa>=0.11.0
Requires-Dist: numpy>=2.2.0
